LICENSE
MANIFEST.in
README.md
requirements.txt
setup.py
moniter_bus/__init__.py
moniter_bus/api.py
moniter_bus/bus.py
moniter_bus/__pycache__/api.cpython-39.pyc
moniter_bus/__pycache__/bus.cpython-39.pyc
moniter_bus/db/all_bus.txt
moniter_bus/db/all_station.txt
moniter_bus_peking.egg-info/PKG-INFO
moniter_bus_peking.egg-info/SOURCES.txt
moniter_bus_peking.egg-info/dependency_links.txt
moniter_bus_peking.egg-info/top_level.txt
tests/__init__.py
tests/api_test.py
tests/bus_test.py