Metadata-Version: 2.1
Name: moniter-bus-peking
Version: 3.0.0
Summary: Get real time bus in Peking
Home-page: https://github.com/dev-J-Ariza/moniter_bus
Author: dev-J-Ariza
Author-email: f_Ariza_dev@outlook.com
License: UNKNOWN
Platform: UNKNOWN
Classifier: Programming Language :: Python :: 3
Classifier: License :: OSI Approved :: MIT License
Classifier: Operating System :: OS Independent
License-File: LICENSE
